deepslide/__init__.py
deepslide/shallowzoom.py
deepslide/version.py
deepslide-0.1.3.dist-info/METADATA
deepslide-0.1.3.dist-info/WHEEL
deepslide-0.1.3.dist-info/top_level.txt
deepslide-0.1.3.dist-info/RECORD
