Metadata-Version: 2.1
Name: deepslide
Version: 0.1.3
Summary: A python toolbox to split whole slide image.
Home-page: https://github.com/xu-kun-cai/deepslide
Author: Xianrui ZHANG and ...
Author-email: zhangxianrui89@gmail.com
License: BSD 3-Clause
Keywords: open ultils for slide image
Platform: UNKNOWN
Classifier: Development Status :: 3 - Alpha
Classifier: Intended Audience :: Developers
Classifier: Intended Audience :: Science/Research
Classifier: Topic :: Software Development :: Build Tools
Classifier: Topic :: Scientific/Engineering :: Artificial Intelligence
Classifier: License :: OSI Approved :: BSD License
Classifier: Programming Language :: Python :: 3.8
Requires-Dist: openslide-python
Requires-Dist: Pillow
Requires-Dist: numpy
Requires-Dist: matplotlib
